hijri/__init__.py
hijri/constant.py
hijri/core.py
hijri/date_utils.py
hijri/version.py
hijri_calendar-0.3.0.dist-info/licenses/LICENSE
hijri_calendar-0.3.0.dist-info/METADATA
hijri_calendar-0.3.0.dist-info/WHEEL
hijri_calendar-0.3.0.dist-info/top_level.txt
hijri_calendar-0.3.0.dist-info/RECORD
