Metadata-Version: 2.4
Name: hijri-calendar
Version: 0.3.0
Summary: A package for converting Hijriah Calendar Day
Author-email: Ryan Febriansyah <15523163@alumni.uii.ac.id>
License: MIT
Project-URL: Homepage, https://github.com/sodrooome/hijriah-converter
Project-URL: Repository, https://github.com/sodrooome/hijriah-converter
Classifier: Development Status :: 4 - Beta
Classifier: Environment :: Console
Classifier: Operating System :: OS Independent
Classifier: Intended Audience :: Developers
Classifier: Natural Language :: English
Classifier: Programming Language :: Python :: 3.10
Classifier: Programming Language :: Python :: 3.11
Classifier: Programming Language :: Python :: 3.12
Requires-Python: >=3.10
License-File: LICENSE
Dynamic: license-file
